custom_html_validator/__init__.py
custom_html_validator/custom_html_validator.py
custom_html_validator-1.0.2.dist-info/LICENSE
custom_html_validator-1.0.2.dist-info/METADATA
custom_html_validator-1.0.2.dist-info/WHEEL
custom_html_validator-1.0.2.dist-info/top_level.txt
custom_html_validator-1.0.2.dist-info/RECORD
